BdRPCpackage.py
BdRPCpackage-1.3.dist-info/LICENSE
BdRPCpackage-1.3.dist-info/METADATA
BdRPCpackage-1.3.dist-info/WHEEL
BdRPCpackage-1.3.dist-info/top_level.txt
BdRPCpackage-1.3.dist-info/RECORD
