Metadata-Version: 2.1
Name: BdRPCpackage
Version: 1.3
Summary: Phylogenetic new sample placement software.
Home-page: https://github.com/Bin-Ma/bd-rpc
Author: mabin
Author-email: 595470377@qq.com
Requires-Python: >=3.6
License-File: LICENSE
Requires-Dist: biopython
Requires-Dist: pandas
Requires-Dist: numpy
Requires-Dist: scipy
Requires-Dist: scikit-learn
Requires-Dist: rpy2
